deeppytorch/__init__.py
deeppytorch-0.0.0.dist-info/METADATA
deeppytorch-0.0.0.dist-info/WHEEL
deeppytorch-0.0.0.dist-info/top_level.txt
deeppytorch-0.0.0.dist-info/RECORD
