Metadata-Version: 2.1
Name: deeppytorch
Version: 0.0.0
Summary: deeppytorch
Home-page: https://www.aliyun.com
